mopipe/__about__.py
mopipe/__init__.py
mopipe/py.typed
mopipe/segment.py
mopipe/core/__init__.py
mopipe/core/analysis/__init__.py
mopipe/core/analysis/pipeline.py
mopipe/core/analysis/py.typed
mopipe/core/analysis/rqa.py
mopipe/core/common/__init__.py
mopipe/core/common/datastructs.py
mopipe/core/common/py.typed
mopipe/core/common/qtm.py
mopipe/core/common/util.py
mopipe/core/data/__init__.py
mopipe/core/data/collator.py
mopipe/core/data/empirical.py
mopipe/core/data/experiment.py
mopipe/core/data/py.typed
mopipe/core/data/reader.py
mopipe/core/segments/__init__.py
mopipe/core/segments/inputs.py
mopipe/core/segments/io.py
mopipe/core/segments/outputs.py
mopipe/core/segments/preprocessor.py
mopipe/core/segments/py.typed
mopipe/core/segments/seg.py
mopipe/core/segments/segmenttypes.py
mopipe-0.2.0.dist-info/METADATA
mopipe-0.2.0.dist-info/WHEEL
mopipe-0.2.0.dist-info/licenses/LICENSE
mopipe-0.2.0.dist-info/RECORD
