Metadata-Version: 2.4
Name: mopipe
Version: 0.2.0
Summary: MoPipe is a Python package for creating a motion capture data analysis pipeline.
Project-URL: Homepage, https://github.com/au-imclab/mopipe
Project-URL: Documentation, https://au-imclab.github.io/mopipe/
Project-URL: Issues, https://github.com/au-imclab/mopipe/issues
Project-URL: Source, https://github.com/au-imclab/mopipe
Project-URL: Changelog, https://github.com/au-imclab/mopipe/blob/main/CHANGELOG.md
Author: zeyus (https://zeyus.com, https://github.com/zeyus), Interacting Minds Centre, Aarhus University (https://interactingminds.au.dk)
License-Expression: MIT
License-File: LICENSE
Classifier: Development Status :: 4 - Beta
Classifier: Intended Audience :: Developers
Classifier: Intended Audience :: Science/Research
Classifier: License :: OSI Approved :: MIT License
Classifier: Operating System :: OS Independent
Classifier: Programming Language :: Python
Classifier: Programming Language :: Python :: 3.9
Classifier: Programming Language :: Python :: 3.10
Classifier: Programming Language :: Python :: 3.11
Classifier: Programming Language :: Python :: 3.12
Classifier: Programming Language :: Python :: 3.13
Classifier: Programming Language :: Python :: 3.14
Classifier: Programming Language :: Python :: Implementation :: CPython
Classifier: Programming Language :: Python :: Implementation :: PyPy
Classifier: Topic :: Scientific/Engineering
Classifier: Topic :: Scientific/Engineering :: Information Analysis
Classifier: Topic :: Scientific/Engineering :: Mathematics
Classifier: Topic :: Scientific/Engineering :: Physics
Classifier: Topic :: Software Development :: Libraries
Classifier: Topic :: Software Development :: Libraries :: Python Modules
Requires-Python: >=3.9
Requires-Dist: joblib
Requires-Dist: pandas
Requires-Dist: scipy
Requires-Dist: strenum; python_version < '3.11'
